fs/googledrivefs/__init__.py
fs/googledrivefs/googledrivefs.py
fs/googledrivefs/opener.py
fs/googledrivefs/search.py
fs_googledrivefs-2.6.1.dist-info/METADATA
fs_googledrivefs-2.6.1.dist-info/WHEEL
fs_googledrivefs-2.6.1.dist-info/entry_points.txt
fs_googledrivefs-2.6.1.dist-info/licenses/LICENSE
fs_googledrivefs-2.6.1.dist-info/RECORD
