Metadata-Version: 2.4
Name: fs.googledrivefs
Version: 2.6.1
Summary: Pyfilesystem2 implementation for Google Drive
Project-URL: Homepage, https://github.com/rkhwaja/fs.googledrivefs
Maintainer-email: Rehan Khwaja <rehan@khwaja.name>
License-Expression: MIT
License-File: LICENSE
Keywords: Pyfilesystem2,filesystem,google
Classifier: Development Status :: 5 - Production/Stable
Classifier: Intended Audience :: Developers
Classifier: Programming Language :: Python :: 3.8
Classifier: Programming Language :: Python :: 3.9
Classifier: Programming Language :: Python :: 3.10
Classifier: Programming Language :: Python :: 3.11
Classifier: Programming Language :: Python :: 3.12
Classifier: Programming Language :: Python :: 3.13
Classifier: Programming Language :: Python :: 3.14
Requires-Python: >=3.8
Requires-Dist: fs>=2.4.13
Requires-Dist: google-api-python-client>=1.7.10
Requires-Dist: google-auth>=1.5.1
